{
    "gammaAccess": {
        "url": "",
        "userName": "",
        "password": ""
    },
    "repositories": [
        {
            "dataDir": "%WORKSPACE%/temp",
            "repository": {
                "uid": "5130cda7015c0921da1692ac63e02669",
                "projectName": "githubdemo_jenkins",
                "languages": [
                    "CPP"
                ],
                "sources": {
                    "baseDir": "%WORKSPACE%",
                    "exclusions": []
                }
            },
            "settings": {
                "additionalOptions": [],
                "includePaths": []
            },
            "modules": {
                "codeissues": [
                    {
                        "name": "gamma_java",
                        "enabled": true,
                        "config": {
                            "rules": [],
                            "options": []
                        }
                    }
                ],
                "unittest": [
                    {
                        "name": "junit",
                        "enabled": true,
                        "config": {
                            "rules": [],
                            "options": [
                                {
                                    "name": "reportDir",
                                    "type": "upload",
                                    "value": "",
                                    "required": true
                                }
                            ]
                        }
                    }
                ],
                "coverage": [
                    {
                        "name": "clover",
                        "enabled": true,
                        "config": {
                            "rules": [],
                            "options": [
                                {
                                    "name": "reportDir",
                                    "type": "upload",
                                    "value": "",
                                    "required": true
                                }
                            ]
                        }
                    }
                ],
                "relevance": [
                    {
                        "name": "relevance",
                        "enabled": true,
                        "config": {
                            "rules": [],
                            "options": []
                        }
                    }
                ]
            }
        }
    ]
}
